ws2812B_spi/__init__.py
ws2812B_spi/example.py
ws2812B_spi/ws2812B_spidrv.py
ws2812B_pkg_ws2812B_spidrv-0.0.1.dist-info/LICENSE.txt
ws2812B_pkg_ws2812B_spidrv-0.0.1.dist-info/METADATA
ws2812B_pkg_ws2812B_spidrv-0.0.1.dist-info/WHEEL
ws2812B_pkg_ws2812B_spidrv-0.0.1.dist-info/top_level.txt
ws2812B_pkg_ws2812B_spidrv-0.0.1.dist-info/RECORD
