Metadata-Version: 2.1
Name: ws2812B-pkg-ws2812B-spidrv
Version: 0.0.1
Summary: ws2812B 8-LED lib
Home-page: https://github.com/schooldevops/python-tutorials
Author: YoungSik KIM
Author-email: ysnet1@nate.com
Project-URL: Bug Tracker, https://github.com/schooldevops/python-tutorials/issues
Classifier: Programming Language :: Python :: 3
Classifier: License :: OSI Approved :: MIT License
Classifier: Operating System :: OS Independent
Requires-Python: >=3.7
License-File: LICENSE.txt
